# 字节码文件结构分析

## 源码结构

```java
package com.xie.jvm.bytecode;

public class MyTest1 {
    private int a = 1;

    public int getA() {
        return a;
    }

    public void setA(int a) {
        this.a = a;
    }
}
```

## 使用javap -verbose 查看对应的字节码

```no
Classfile /Users/xiexiaofei/work_sapce/idea_work/jvm_lecture/target/classes/com/xie/jvm/bytecode/MyTest1.class
  Last modified 2020年2月21日; size 487 bytes
  MD5 checksum 0be53da640840e2771743a39ddd3cf32
  Compiled from "MyTest1.java"
public class com.xie.jvm.bytecode.MyTest1
  minor version: 0
  major version: 52
  flags: (0x0021) ACC_PUBLIC, ACC_SUPER
  this_class: #3                          // com/xie/jvm/bytecode/MyTest1
  super_class: #4                         // java/lang/Object
  interfaces: 0, fields: 1, methods: 3, attributes: 1
Constant pool:
   #1 = Methodref          #4.#20         // java/lang/Object."<init>":()V
   #2 = Fieldref           #3.#21         // com/xie/jvm/bytecode/MyTest1.a:I
   #3 = Class              #22            // com/xie/jvm/bytecode/MyTest1
   #4 = Class              #23            // java/lang/Object
   #5 = Utf8               a
   #6 = Utf8               I
   #7 = Utf8               <init>
   #8 = Utf8               ()V
   #9 = Utf8               Code
  #10 = Utf8               LineNumberTable
  #11 = Utf8               LocalVariableTable
  #12 = Utf8               this
  #13 = Utf8               Lcom/xie/jvm/bytecode/MyTest1;
  #14 = Utf8               getA
  #15 = Utf8               ()I
  #16 = Utf8               setA
  #17 = Utf8               (I)V
  #18 = Utf8               SourceFile
  #19 = Utf8               MyTest1.java
  #20 = NameAndType        #7:#8          // "<init>":()V
  #21 = NameAndType        #5:#6          // a:I
  #22 = Utf8               com/xie/jvm/bytecode/MyTest1
  #23 = Utf8               java/lang/Object
{
  public com.xie.jvm.bytecode.MyTest1();
    descriptor: ()V
    flags: (0x0001) ACC_PUBLIC
    Code:
      stack=2, locals=1, args_size=1
         0: aload_0
         1: invokespecial #1                  // Method java/lang/Object."<init>":()V
         4: aload_0
         5: iconst_1
         6: putfield      #2                  // Field a:I
         9: return
      LineNumberTable:
        line 4: 0
        line 5: 4
      LocalVariableTable:
        Start  Length  Slot  Name   Signature
            0      10     0  this   Lcom/xie/jvm/bytecode/MyTest1;

  public int getA();
    descriptor: ()I
    flags: (0x0001) ACC_PUBLIC
    Code:
      stack=1, locals=1, args_size=1
         0: aload_0
         1: getfield      #2                  // Field a:I
         4: ireturn
      LineNumberTable:
        line 8: 0
      LocalVariableTable:
        Start  Length  Slot  Name   Signature
            0       5     0  this   Lcom/xie/jvm/bytecode/MyTest1;

  public void setA(int);
    descriptor: (I)V
    flags: (0x0001) ACC_PUBLIC
    Code:
      stack=2, locals=2, args_size=2
         0: aload_0
         1: iload_1
         2: putfield      #2                  // Field a:I
         5: return
      LineNumberTable:
        line 12: 0
        line 13: 5
      LocalVariableTable:
        Start  Length  Slot  Name   Signature
            0       6     0  this   Lcom/xie/jvm/bytecode/MyTest1;
            0       6     1     a   I
}
SourceFile: "MyTest1.java"
```

## 使用工具查看.class的16进制字节码

```no
CA FE BA BE 00 00 00 34 00 18 0A 00 04 00 14 09 00 03 00 15 07 00 16 07 00 17 01 00 01 61 01 00  
01 49 01 00 06 3C 69 6E 69 74 3E 01 00 03 28 29 56 01 00 04 43 6F 64 65 01 00 0F 4C 69 6E 65 4E  
75 6D 62 65 72 54 61 62 6C 65 01 00 12 4C 6F 63 61 6C 56 61 72 69 61 62 6C 65 54 61 62 6C 65 01  
00 04 74 68 69 73 01 00 1E 4C 63 6F 6D 2F 78 69 65 2F 6A 76 6D 2F 62 79 74 65 63 6F 64 65 2F 4D  
79 54 65 73 74 31 3B 01 00 04 67 65 74 41 01 00 03 28 29 49 01 00 04 73 65 74 41 01 00 04 28 49  
29 56 01 00 0A 53 6F 75 72 63 65 46 69 6C 65 01 00 0C 4D 79 54 65 73 74 31 2E 6A 61 76 61 0C 00  
07 00 08 0C 00 05 00 06 01 00 1C 63 6F 6D 2F 78 69 65 2F 6A 76 6D 2F 62 79 74 65 63 6F 64 65 2F  
4D 79 54 65 73 74 31 01 00 10 6A 61 76 61 2F 6C 61 6E 67 2F 4F 62 6A 65 63 74 00 21 00 03 00 04  
00 00 00 01 00 02 00 05 00 06 00 00 00 03 00 01 00 07 00 08 00 01 00 09 00 00 00 38 00 02 00 01  
00 00 00 0A 2A B7 00 01 2A 04 B5 00 02 B1 00 00 00 02 00 0A 00 00 00 0A 00 02 00 00 00 04 00 04  
00 05 00 0B 00 00 00 0C 00 01 00 00 00 0A 00 0C 00 0D 00 00 00 01 00 0E 00 0F 00 01 00 09 00 00  
00 2F 00 01 00 01 00 00 00 05 2A B4 00 02 AC 00 00 00 02 00 0A 00 00 00 06 00 01 00 00 00 08 00  
0B 00 00 00 0C 00 01 00 00 00 05 00 0C 00 0D 00 00 00 01 00 10 00 11 00 01 00 09 00 00 00 3E 00  
02 00 02 00 00 00 06 2A 1B B5 00 02 B1 00 00 00 02 00 0A 00 00 00 0A 00 02 00 00 00 0C 00 05 00  
0D 00 0B 00 00 00 16 00 02 00 00 00 06 00 0C 00 0D 00 00 00 00 00 06 00 05 00 06 00 01 00 01 00  
12 00 00 00 02 00 13
```

## Class字节码中两种数据数据类型

- 字节数据直接量：这是基本的数据类型。共细分为u1,u2,u4,u8四种，分别代表连续的1个字节，2个字节，4个字节，8个字节组成的整体数据。
- 表（数组）：表是由多个基本数据或其他表，按照既定顺序组成的大的数据集合。表是有结构的，它的结构体现在：组成表的成分所在的位置和顺序都已经严格定义好的。

## 字段表结构

```no
field_info{
    u2 access_flags;
    u2 name_index;
    u2 decriptor_index;
    u2 attributes_count;
    attribute_info attributes[attributes_count];
}
```

## 方法表结构

```no
method_info{
    u2 access_flags;
    u2 name_index;
    u2 decriptor_index;
    u2 attributes_count;
    attribute_info attributes[attributes_count];
}
```

## 方法的属性结构

```no
attribute_info{
    u2 attribute_name_index;
    u4 attribute_length;
    u1 info[attribute_lenght];
}
```

JVM预定义了部分attribute,但是编译器自己也可以实现自己的attribute写入class文件里，供运行时使用。不同的attribute通过`attribute_name_index`来区分。

## Code结构

code attribute 的作用是保存该方法的结构，如所对应的字节码

```no
code_attribute{
    u2 attribute_name_index;
    u4 attribute_length;
    u2 max_stack;
    u2 max_locals;
    u4 code_length;
    u1 code[code_length];
    u2 excetipon_table_length;
    {
        u2 start_pc;
        u2 enc_pc;
        u2 handler_pc;
        u2 catch_type;
    }exception_table[exception_table_length];
    u2 attributes_count;
    attribute_info attributes[attributes_count];
}
```

1. attribute_length 表示attribute所包含的字节数，不包含`attribute_name_index`和`attribute_length`字段；
2. max_stack 表示这个方法运行的任何时刻所能达到的操作数栈的最大深度；
3. max_locals 表示方法执行期间创建的局部变量的数目，包含用来表示传入的参数的局部变量；
4. code_length 表示该方法所包含的字节码的字节数以及具体的指令码；
5. 具体字节码即是该方法被调用时，虚拟机所执行的字节码；
6. exception_table,这里存放的是处理异常的信息；
7. 每个exception_table 表项由 start_pc、end_pc、handler_pc、catch_type组成；
8. start_pc和end_pc表示在code数组中从start_pc到end_pc处（包含start_pc,不包含end_pc)的指令抛出的异常会由这个表项来处理；
9. handler_pc 表示处理异常的代码开始处。catch_type表示会被处理的异常类型，它指向常量池里的一个异常类。当catch_type为0时，表示处理所有的异常。
10. 接下来是该方法的附加属性
11. LineNumberTable：这个属性用来表示code数组中的字节码和java代码行数之间的关系。这个属性可以用来在调试的时候定位代码执行的行数。

    ```no
    LineNumberTable_attribute{
        u2 attribute_name_index;
        u4 attribute_length;
        u2 line_number_table_length;
        {
            u2 start_pc;
            u2 line_number;
        }line_number_table[line_number_table_length];
    }
    ```

## Java字节码整体结构

顺序模块 | 字节数
---|---
Magic Number| 4个字节
Version | 2+2个字节
Constant Pool | 2+n个字节
Access Flags | 2个字节
This Class Name | 2个字节
Super Class Name | 2个字节
Interface | 2+n个字节
Fileds | 2+n个字节
Methods | 2+n个字节
Attributes | 2+n个字节

对应的另一张表结构

类型 | 名称|数量
---|--- |---
u4| magic(魔数)|1
u2 |minor_version(次版本号)|1
u2 |major_version(主版本号) |1
u2 | constant_pool_count常量池个数|1
cp_info | constant_pool(常量池表)|constant_pool_count-1
u2|access_flags(类的访问控制权限)|1
u2|this_class(类名)|1
u2|super_class(父类名)|1
u2|interfaces_count(接口个数)|1
interface_info|interfaces(接口名)|interfaces_count
u2|fileds_count(域个数)|1
field_info|fileds(域的表)|fields_count
u2|methods_count(方法的个数)|1
method_info|methods(方法的表)|methods_count
u2|attributes_count(附加属性的个数)|1
attribute_info|attributs(附加属性的表)|attributes_count

## 常量池中的14种常量项的结构总表

<html>
<!--在这里插入内容-->
<table>
    <tr>
        <th style="width: 280px;">常量</th>
        <th style="width: 200px;">项目</th>
        <th style="width: 50px;">类型</th>
        <th>描述</th>
    </tr >
    <tr >
        <td rowspan="3">CONSTANT_Utf8_info</td>
        <td>tag</td>
        <td>u1</td>
        <td>值为1</td>
    </tr>
    <tr >
        <td>length</td>
        <td>u2</td>
        <td>UTF-8编码的字符串占用的字节数</td>
    </tr>
    <tr >
        <td>bytes</td>
        <td>u4</td>
        <td>长度为lenght的UTF-8编码的字符串</td>
    </tr>
    <tr >
        <td rowspan="2">CONSTANT_Integer_info</td>
        <td>tag</td>
        <td>u1</td>
        <td>值为3</td>
    </tr>
    <tr >
        <td>bytes</td>
        <td>u4</td>
        <td>按照高位在前存储的int值</td>
    </tr>
    <tr >
        <td rowspan="2">CONSTANT_Float_info</td>
        <td>tag</td>
        <td>u1</td>
        <td>值为4</td>
    </tr>
    <tr >
        <td>bytes</td>
        <td>u4</td>
        <td>按照高位在前存储的float值</td>
    </tr>
    <tr >
        <td rowspan="2">CONSTANT_Long_info</td>
        <td>tag</td>
        <td>u1</td>
        <td>值为5</td>
    </tr>
    <tr >
        <td>bytes</td>
        <td>u8</td>
        <td>按照高位在前存储的long值</td>
    </tr>
    <tr >
        <td rowspan="2">CONSTANT_Double_info</td>
        <td>tag</td>
        <td>u1</td>
        <td>值为6</td>
    </tr>
    <tr >
        <td>bytes</td>
        <td>u8</td>
        <td>按照高位在前存储的double值</td>
    </tr>
    <tr >
        <td rowspan="2">CONSTANT_Class_info</td>
        <td>tag</td>
        <td>u1</td>
        <td>值为7</td>
    </tr>
    <tr >
        <td>index</td>
        <td>u2</td>
        <td>指向全限定名常量项的索引</td>
    </tr>
    <tr >
        <td rowspan="2">CONSTANT_String_info</td>
        <td>tag</td>
        <td>u1</td>
        <td>值为8</td>
    </tr>
    <tr >
        <td>index</td>
        <td>u2</td>
        <td>指向字符串字面量的索引</td>
    </tr>
    <tr >
        <td rowspan="3">CONSTANT_Fieldref_info</td>
        <td>tag</td>
        <td>u1</td>
        <td>值为9</td>
    </tr>
    <tr >
        <td>index</td>
        <td>u2</td>
        <td>指向声明字段的类或者接口描述符CONSTANT_Class_info的索引项</td>
    </tr>
    <tr >
        <td>index</td>
        <td>u2</td>
        <td>指向字段描述符CONSTANT_NameAndType的索引项</td>
    </tr>
    <tr >
        <td rowspan="3">CONSTANT_Methodref_info</td>
        <td>tag</td>
        <td>u1</td>
        <td>值为10</td>
    </tr>
    <tr >
        <td>index</td>
        <td>u2</td>
        <td>指向声明方法的类的描述符CONSTANT_Class_info的索引项</td>
    </tr>
    <tr >
        <td>index</td>
        <td>u2</td>
        <td>指向名称及类型描述符CONSTANT_NameAndType的索引项</td>
    </tr>
    <tr >
        <td rowspan="3">CONSTANT_Interface-Methodref_info</td>
        <td>tag</td>
        <td>u1</td>
        <td>值为11</td>
    </tr>
    <tr >
        <td>index</td>
        <td>u2</td>
        <td>指向声明方法的接口描述符CONSTANT_Class_info的索引项</td>
    </tr>
    <tr >
        <td>index</td>
        <td>u2</td>
        <td>指向名称及类型描述符CONSTANT_NameAndType的索引项</td>
    </tr>
    <tr >
        <td rowspan="3">CONSTANT_Name-AndType_info</td>
        <td>tag</td>
        <td>u1</td>
        <td>值为12</td>
    </tr>
    <tr >
        <td>index</td>
        <td>u2</td>
        <td>指向该字段或方法名称常量项的索引</td>
    </tr>
    <tr >
        <td>index</td>
        <td>u2</td>
        <td>指向该字段或方法描述符常量项的索引</td>
    </tr>
    <tr >
        <td rowspan="3">CONSTANT_Method-Handle_info</td>
        <td>tag</td>
        <td>u1</td>
        <td>值为15</td>
    </tr>
    <tr >
        <td>reference_kind</td>
        <td>u1</td>
        <td>值必须在1-9之间(包括1和9)，它决定了方法句柄的类型。方法句柄类型的值表示方法句柄的字节码行为</td>
    </tr>
    <tr >
        <td>reference_index</td>
        <td>u2</td>
        <td>值必须是对常量池的有效索引</td>
    </tr>
    <tr >
        <td rowspan="2">CONSTANT_Method-Type_info</td>
        <td>tag</td>
        <td>u1</td>
        <td>值为16</td>
    </tr>
    <tr >
        <td>descriptor_index</td>
        <td>u2</td>
        <td>值必须是对常量池的有效索引，常量池在该处的项必须是CONSTANT_Utf8_info结构，表示方法的描述符</td>
    </tr>
    <tr >
        <td rowspan="3">CONSTANT_Invoke-Dynamic_info</td>
        <td>tag</td>
        <td>u1</td>
        <td>值为18</td>
    </tr>
    <tr >
        <td>bootstrap_method_attr_index</td>
        <td>u2</td>
        <td>值必须是对当前class文件中引导方法表的bootstrap_methods[]数组的有效索引</td>
    </tr>
    <tr >
        <td>name_and_type_index</td>
        <td>u2</td>
        <td>值必须是对常量池的有效索引，常量池在该处的项必须是CONSTANT_NameAndType_info结构，表示方法名和方法描述符</td>
    </tr>
</table>
</html>

## 分析

1. 使用`javap -verbose` 命令分析一个字节码文件时，将会分析该字节码文件的魔数、版本号、常量池、类信息、类的构造方法、类中的方法信息、类变量与成员变量等信息。
2. 魔数：所有的.class字节码文件的前4个字节都是魔数，魔数值为固定值：0xCAFEBABE
3. 魔数之后的4个字节是版本信息，前两个字节表示minor version(次版本号),后两个字节表示major version(主版本号)。这里的版本号为`00 00 00 34`，换算成10进制，表示此版本号为0，主版本号为52。可以用过`java -version`来验证。
4. 常量池(Constant pool):紧接着主版本号之后的就是常量池的入口。一个Java类定义的很多信息都是由常量池来维护和描述的。可以将常量池看作是Class文件的资源仓库，比如说Java类中定义的方法与变量信息，都是存储在常量池中。常量池中主要存储两类常量：字面量与符号引用。字面量如文本字符串，Java中声明为final的常量值等，而符号引用如类和接口全局限定名、字段的名称和描述符，方法的名称和描述符等。
5. 常量池的总体结构：Java类对应的常量池主要池数量与常量池数组这两部分共同构成。常量池数量紧跟在主版本号后面，占据2个字节；常量池数组则紧跟在常量池数量之后。常量池数组与一般的数组不同的是，常量池数组中不同的元素的类型、结构都是不同的，长度当然也就不同；但是，每一种元素的第一个数据都是一个u1类型，该字节是个标志位，占据1个字节。JVM在解析常量池时，会根据这个u1类型来获取元素具体类型。值得注意的是，常量池数组中元素的个数 = 常量池树 - 1(其中0暂时不适用)，目的是满足某些常量池索引值的数据在特定情况下需要表达**不引用任何一个常量池**的含义；根本原因在于，索引为0也是一个常量(保留常量)，只不过它不位于常量表中，这个常量就对应null值；所以，常量池的索引从1而非0开始。
6. 在JVM规范中，每个变量/字段都有描述信息，描述信息主要的作用就是描述字段的数据类型、方法的参数列表（包括数量、类型与顺序）与返回值。根据描述符规则，基本类型和代表无返回值的void类型都用一个大写字符来表示，对象类型则使用字符L加对象的全限定名称来表示。为了压缩字节码文件的体积，对于基本数据类型，JVM都只使用一个大写字母来表示，如下所示：`B - byte,C - char,D - double,F - float,I - int,J - long,S - short,Z - boolean,V - void,L - 对象类型`,如`Ljava/lang/String;`
7. 对于数组类型来说，每一个维度使用一个前置的`[`来表示，如`int[]`被记录为`[I`,`String[]`被记录为`[[Ljava/lang/String;`
8. 用描述符描述方法，按照先参数列表，后返回值的顺序来描述。参数列表按照参数的严格顺序放在一组`()`之内，如方法：`String getRealNameByIdAndNickname(int id,String name)`的描述符为：`(I,Ljava/lang/Object) Ljava/lang/String;`

## IDEA 可使用jclasslib工具查看字节码
