# 类加载

类的加载指的是将类的`.class`文件中的二进制数据读入到内存中，将其放在运行时数据区的方法区内，然后在内存中创建一个`java.lang.Class`对象（规范并未说明`Class`对象位于哪里，`HotSpot`虚拟机将其放在了方法区中）用来封装类的方法区的数据结构。

加载`.class`文件的方式：

- 从本地系统中直接加载；
- 通过网络下载`.class`文件；
- 从`zip、jar`等归档文件中加载`.class`文件;
- 从专有数据库中提取`.class`文件
- 将Java源文件动态编译为`.class`文件

类加载额外说明

- 在`Java`代码中，类型的加载、连接与初始化过程都是在程序运行期间完成的。
- 提供了更大的灵活性，增加了更多的可能性。
- `Java`虚拟机与程序的生命周期。
- 在如下几种情况下，`Java`虚拟机将结束生命周期：

    1. 执行了`System.exit()`方法；
    2. 程序正常结束；
    3. 程序在执行过程中遇到了异常或错误而异常终止；
    4. 由于操作系统出现错误而导致`Java`虚拟机进程终止；

## 类的加载、连接与初始化

- 加载：查找并加载类的二进制数据；
- 连接：
    1. 验证：确保被加载的类的正确性；
    2. 准备：为类的**静态变量**分配内存，并初始化为**默认值**；
    3. 解析：**把类的符号引用转换为直接引用**;
- 初始化：**为类的静态变量赋予正确的初始值**；
- 实例化：为新的对象分配内存，为实例变量赋默认值，为实例变脸赋正确的初始值
- `Java`程序对类的使用方式可分为两种
    1. 主动使用(七种)
        - 创建类的实例;
        - 访问某个类或接口静态常量，或者对该静态变量赋值;
        - 调用类的静态方法;
        - 反射(如 `Class.forName("com.test.Test"))`;
        - 初始化一个类的子类;
        - `Java`虚拟机启动时被标明为启动类的类(`Java Test`);
        - JDK1.7 开始提供的动态语言支持：`java.lang.invoke.MethodHandle`实例的解析结果`REF_getStatic,REF_pustatic,REF_invokeStatic`句柄对应的类没有初始化，则初始化;
    2. 被动使用
        - 除了主动使用的七种情况，其他使用`Java`类的方法都被看做是对类的**被动使用**，都不会导致类的**初始化**
- 所有的`Java`虚拟机实现必须在每个类或接口被`Java`程序“首次主动使用”时才初始化它们

## 代码案例-查看类加载

```java
package com.xie.jvm.classloader;

/**
 * 对于静态字段来说，只有直接定义了该字段的类才会被初始化。
 * 当一个类在初始化时，要求其父类全部都已被初始化完毕。
 */
public class MyTest1 {
    public static void main(String[] args) {
        System.out.println(MyChild1.str);

        /**
         * MyParent1 static block
         * Hello world
         */
    }
}

class MyParent1 {
    public static String str = "Hello world";

    static {
        System.out.println("MyParent1 static block");
    }
}

class MyChild1 extends MyParent1 {
    public static String str2 = "welcome";

    static {
        System.out.println("MyChild1 static block");
    }
}
```

这里的输出体现了主动使用的第5中情况，即对于静态字段来说，只有直接定义了该字段的类才会被初始化。
当我们打印str2时，结果如下：

```java
package com.xie.jvm.classloader;

/**
 * 对于静态字段来说，只有直接定义了该字段的类才会被初始化。
 * 当一个类在初始化时，要求其父类全部都已被初始化完毕。
 */
public class MyTest1 {
    public static void main(String[] args) {
        System.out.println(MyChild1.str2);

        /**
         * MyParent1 static block
         * MyChild1 static block
         * welcome
         */
    }
}

class MyParent1 {
    public static String str = "Hello world";

    static {
        System.out.println("MyParent1 static block");
    }
}

class MyChild1 extends MyParent1 {
    public static String str2 = "welcome";

    static {
        System.out.println("MyChild1 static block");
    }
}
```

## 运行参数：-XX:+TraceClassLoading

用于追踪类的加载信息并打印出来,如下显示：

```no
[Opened /Library/Java/JavaVirtualMachines/jdk1.8.0_201.jdk/Contents/Home/jre/lib/rt.jar]
[Loaded java.lang.Object from /Library/Java/JavaVirtualMachines/jdk1.8.0_201.jdk/Contents/Home/jre/lib/rt.jar]
[Loaded java.io.Serializable from /Library/Java/JavaVirtualMachines/jdk1.8.0_201.jdk/Contents/Home/jre/lib/rt.jar]
[Loaded java.lang.Comparable from /Library/Java/JavaVirtualMachines/jdk1.8.0_201.jdk/Contents/Home/jre/lib/rt.jar]
[Loaded java.lang.CharSequence from /Library/Java/JavaVirtualMachines/jdk1.8.0_201.jdk/Contents/Home/jre/lib/rt.jar]
....
....
....
[Loaded com.xie.jvm.classloader.MyParent1 from file:/Users/xiexiaofei/work_sapce/idea_work/jvm_lecture/target/classes/]
[Loaded com.xie.jvm.classloader.MyChild1 from file:/Users/xiexiaofei/work_sapce/idea_work/jvm_lecture/target/classes/]
MyParent1 static block
Hello world
[Loaded java.util.ArrayList$Itr from /Library/Java/JavaVirtualMachines/jdk1.8.0_201.jdk/Contents/Home/jre/lib/rt.jar]
```

`-XX:+<option>`：表示开启option选项，`-XX:-<option>`：表示关闭option选项，`-XX:<option>=<value>`：表示将option选项的值设置为value

## 常量的本质含义与反编译及助记符

常量在编译阶段会存入到调用这个常量的方法所在类的常量池中，本质上，调用类并没有直接引用到定义常量的类，因此并不会触发定义常量的类的初始化。

```java
package com.xie.jvm.classloader;

/**
 * 常量在编译阶段会存入到调用这个常量的方法所在类的常量池中，
 * 本质上，调用类并没有直接引用到定义常量的类，因此并不会触发定义常量的类的初始化。
 *
 * 注意：这个指的将常量存放到了MyTest2的常量池中，之后MyTest2与MyParent2就没有任何关系了
 * 甚至，我们可以将MyParent2的class文件删除
 *
 * 助记符：
 * ldc 表示将int,float或是String类型的常量从常量池中推送至栈顶
 * bipush 表示将单字节(-128-127)的常量值推送至栈顶
 * sipush 表示将一个短整型(-32768-32767)推送至栈顶
 * iconst_1 表示将int类型1 推送至栈顶，(iconst_1-iconst_5)
 */
public class MyTest2 {
    public static void main(String[] args) {
        System.out.println(MyParent2.str);
        System.out.println(MyParent2.i);
        System.out.println(MyParent2.m1);
        System.out.println(MyParent2.m2);
        System.out.println(MyParent2.m3);
    }
}

class MyParent2 {
    public static final String str = "hello world";
    public static final short s = 127;
    public static final int i = 128;
    public static final int m1 = 1;
    public static final int m2 = 5;
    public static final int m3 = 6;

    static {
        System.out.println("MyParent2 static block");
    }
}

```

使用javap命令进行反编译， javap -c MyTest2.class可以得到如下信息：

```no
Compiled from "MyTest2.java"
public class com.xie.jvm.classloader.MyTest2 {
  public com.xie.jvm.classloader.MyTest2();
    Code:
       0: aload_0
       1: invokespecial #1                  // Method java/lang/Object."<init>":()V
       4: return

  public static void main(java.lang.String[]);
    Code:
       0: getstatic     #2                  // Field java/lang/System.out:Ljava/io/PrintStream;
       3: ldc           #4                  // String hello world
       5: invokevirtual #5                  // Method java/io/PrintStream.println:(Ljava/lang/String;)V
       8: getstatic     #2                  // Field java/lang/System.out:Ljava/io/PrintStream;
      11: sipush        128
      14: invokevirtual #6                  // Method java/io/PrintStream.println:(I)V
      17: getstatic     #2                  // Field java/lang/System.out:Ljava/io/PrintStream;
      20: iconst_1
      21: invokevirtual #6                  // Method java/io/PrintStream.println:(I)V
      24: getstatic     #2                  // Field java/lang/System.out:Ljava/io/PrintStream;
      27: iconst_5
      28: invokevirtual #6                  // Method java/io/PrintStream.println:(I)V
      31: getstatic     #2                  // Field java/lang/System.out:Ljava/io/PrintStream;
      34: bipush        6
      36: invokevirtual #6                  // Method java/io/PrintStream.println:(I)V
      39: return
}
```

可以看到 inconst_i 的后缀 i 的范围是 0-5，当超过 5 时，就会变成 bipush。
这些助记符都是基于类实现的，在jdk的rt.jar中，比如iconst->com.sun.org.apache.bcel.internal.generic.ICONST，bipush->com.sun.org.apache.bcel.internal.generic.BIPUSH...

## 编译期常量与运行期常量的区别及数组创建本质分析

对于常量在编译器无法确定的，需要在运行期才能确定，那么在调用时，就会初始化这个包含常量的类。

```java
package com.xie.jvm.classloader;

import java.util.UUID;

/**
 * 当一个常量的值并非编译期间可以确定的，那么其值就不会被放到调用类的常量池中，
 * 这时在程序运行时，会导致主动使用这个常量所在的类，显然会导致这个类被初始化
 */
public class MyTest3 {
    public static void main(String[] args) {
        System.out.println(MyParent3.str);

        /**
         * MyParent3 static block
         * 0bcd2517-ca28-4ee0-a1cf-43dcbca87957
         */
    }
}

class MyParent3 {
    public static final String str = UUID.randomUUID().toString();

    static {
        System.out.println("MyParent3 static block");
    }
}
```

对于数组实例来说，其类型是由JVM在运行期动态生成的，表示为[Lcom.xie.jvm.classloader.MyParent4，因此并不会初始化包含常量的类

```java
package com.xie.jvm.classloader;

/**
 * 对于数组实例来说，其类型是由JVM在运行期动态生成的，表示为[Lcom.xie.jvm.classloader.MyParent4;
 *
 * 对于数组来说，JavaDoc经常讲构成数组的元素为Component,实际上就是将数组降低一个维度后的类型
 *
 */
public class MyTest4 {
    public static void main(String[] args) {
        MyParent4[] myParent4 = new MyParent4[1];
        System.out.println(myParent4.getClass());
        MyParent4[][] myParent4s = new MyParent4[1][1];
        System.out.println(myParent4s.getClass());

        System.out.println(myParent4.getClass().getSuperclass());
        System.out.println(myParent4s.getClass().getSuperclass());

        System.out.println("===========");

        int[] ints = new int[1];
        System.out.println(ints.getClass());
        System.out.println(ints.getClass().getSuperclass());

        /**
         * class [Lcom.xie.jvm.classloader.MyParent4;
         * class [[Lcom.xie.jvm.classloader.MyParent4;
         * class java.lang.Object
         * class java.lang.Object
         * ===========
         * class [I
         * class java.lang.Object
         */
    }
}

class MyParent4 {
    static {
        System.out.println("MyParent4 static block");
    }
}
```

将MyTest4进行反编译后，得到的结果：

```no
Compiled from "MyTest4.java"
public class com.xie.jvm.classloader.MyTest4 {
  public com.xie.jvm.classloader.MyTest4();
    Code:
       0: aload_0
       1: invokespecial #1                  // Method java/lang/Object."<init>":()V
       4: return

  public static void main(java.lang.String[]);
    Code:
       0: iconst_1
       1: anewarray     #2                  // class com/xie/jvm/classloader/MyParent4
       4: astore_1
       5: getstatic     #3                  // Field java/lang/System.out:Ljava/io/PrintStream;
       8: aload_1
       9: invokevirtual #4                  // Method java/lang/Object.getClass:()Ljava/lang/Class;
      12: invokevirtual #5                  // Method java/io/PrintStream.println:(Ljava/lang/Object;)V
      15: iconst_1
      16: iconst_1
      17: multianewarray #6,  2             // class "[[Lcom/xie/jvm/classloader/MyParent4;"
      21: astore_2
      22: getstatic     #3                  // Field java/lang/System.out:Ljava/io/PrintStream;
      25: aload_2
      26: invokevirtual #4                  // Method java/lang/Object.getClass:()Ljava/lang/Class;
      29: invokevirtual #5                  // Method java/io/PrintStream.println:(Ljava/lang/Object;)V
      32: getstatic     #3                  // Field java/lang/System.out:Ljava/io/PrintStream;
      35: aload_1
      36: invokevirtual #4                  // Method java/lang/Object.getClass:()Ljava/lang/Class;
      39: invokevirtual #7                  // Method java/lang/Class.getSuperclass:()Ljava/lang/Class;
      42: invokevirtual #5                  // Method java/io/PrintStream.println:(Ljava/lang/Object;)V
      45: getstatic     #3                  // Field java/lang/System.out:Ljava/io/PrintStream;
      48: aload_2
      49: invokevirtual #4                  // Method java/lang/Object.getClass:()Ljava/lang/Class;
      52: invokevirtual #7                  // Method java/lang/Class.getSuperclass:()Ljava/lang/Class;
      55: invokevirtual #5                  // Method java/io/PrintStream.println:(Ljava/lang/Object;)V
      58: getstatic     #3                  // Field java/lang/System.out:Ljava/io/PrintStream;
      61: ldc           #8                  // String ===========
      63: invokevirtual #9                  // Method java/io/PrintStream.println:(Ljava/lang/String;)V
      66: iconst_1
      67: newarray       int
      69: astore_3
      70: getstatic     #3                  // Field java/lang/System.out:Ljava/io/PrintStream;
      73: aload_3
      74: invokevirtual #4                  // Method java/lang/Object.getClass:()Ljava/lang/Class;
      77: invokevirtual #5                  // Method java/io/PrintStream.println:(Ljava/lang/Object;)V
      80: getstatic     #3                  // Field java/lang/System.out:Ljava/io/PrintStream;
      83: aload_3
      84: invokevirtual #4                  // Method java/lang/Object.getClass:()Ljava/lang/Class;
      87: invokevirtual #7                  // Method java/lang/Class.getSuperclass:()Ljava/lang/Class;
      90: invokevirtual #5                  // Method java/io/PrintStream.println:(Ljava/lang/Object;)V
      93: return
}
```

助记符：

- anewarray：表示创建一个引用类型的(如类、接口、数组)数组，并将其引用值压入栈顶；
- newarray：表示创建一个指定的原始类型(如int、float、char等)的数组，并将其引用值压入栈顶;
